LICENSE.pdf
MANIFEST.in
README.md
setup.py
aps/__init__.py
aps/metrology/__init__.py
aps/metrology/__main__.py
aps/metrology/ltp/__init__.py
aps/metrology/ltp/kb/__init__.py
aps/metrology/ltp/kb/bl/__init__.py
aps/metrology/ltp/kb/bl/automate_LTP_KB.py
aps/metrology/ltp/kb/scripts/__init__.py
aps/metrology/ltp/kb/scripts/main_automate_LTP_KB.py
aps/metrology/ltp/kb/widgets/ALK_display_results_widget.py
aps/metrology/ltp/kb/widgets/ALK_start_data_analysis_widget.py
aps/metrology/ltp/kb/widgets/__init__.py
aps/metrology/ltp/response_function/__init__.py
aps/metrology/ltp/stability/__init__.py
aps_metrology.egg-info/PKG-INFO
aps_metrology.egg-info/SOURCES.txt
aps_metrology.egg-info/dependency_links.txt
aps_metrology.egg-info/namespace_packages.txt
aps_metrology.egg-info/not-zip-safe
aps_metrology.egg-info/requires.txt
aps_metrology.egg-info/top_level.txt