Metadata-Version: 1.2
Name: aps-metrology
Version: 0.0.2
Summary: Utilities for the APS Metrology Laboratory
Home-page: https://github.com/APS-XSD-OPT-Group/Metrology
Author: Luca Rebuffi, Xianbo Shi, Zhi Qiao
Author-email: lrebuffi@anl.gov
Maintainer: XSD-OPT Group @ APS-ANL
Maintainer-email: lrebuffi@anl.gov
License: BSD-3
Download-URL: https://github.com/APS-XSD-OPT-Group/Metrology
Keywords: dictionary,glossary,synchrotronsimulation
Platform: UNKNOWN
Classifier: Development Status :: 4 - Beta
Classifier: License :: OSI Approved :: BSD License
Classifier: Natural Language :: English
Classifier: Environment :: Console
Classifier: Environment :: Plugins
Classifier: Programming Language :: Python :: 3.8
Classifier: Topic :: Scientific/Engineering :: Visualization
Classifier: Intended Audience :: Science/Research
